primapy_saffron/__init__.py
primapy_saffron-0.1.0.dist-info/METADATA
primapy_saffron-0.1.0.dist-info/WHEEL
primapy_saffron-0.1.0.dist-info/RECORD
